json_logger/__init__.py
json_logger/logger.py
json_logger/setup.py
tests/__init__.py
tests/test_logger.py
json_logger_loki-0.2.0.dist-info/LICENSE
json_logger_loki-0.2.0.dist-info/METADATA
json_logger_loki-0.2.0.dist-info/WHEEL
json_logger_loki-0.2.0.dist-info/top_level.txt
json_logger_loki-0.2.0.dist-info/RECORD
