Metadata-Version: 2.1
Name: json-logger-loki
Version: 0.2.0
Summary: A JSON logger with OpenTelemetry and Loki support
Home-page: https://github.com/rafaelbrandaof/json_logger_loki
Author: Rafael Brandao Ferreira
Author-email: Rafael Brandao Ferreira <rafaelbrandaof@gmail.com>
Classifier: Programming Language :: Python :: 3
Classifier: License :: OSI Approved :: MIT License
Classifier: Operating System :: OS Independent
Requires-Python: >=3.7
License-File: LICENSE
Requires-Dist: flake8 >=5.0.4
Requires-Dist: opentelemetry-api
Requires-Dist: pylint >=2.13.9
Requires-Dist: pytest >=7.4.4
Requires-Dist: requests
Requires-Dist: setuptools >=68.0.0
